lazy_alchemy/VERSION
lazy_alchemy/__init__.py
lazy_alchemy/lazy_alchemy.py
tests/__init__.py
tests/seed_db.py
tests/test_lazy_orm.py
lazy_alchemy-1.0.3.dist-info/LICENSE
lazy_alchemy-1.0.3.dist-info/METADATA
lazy_alchemy-1.0.3.dist-info/WHEEL
lazy_alchemy-1.0.3.dist-info/top_level.txt
lazy_alchemy-1.0.3.dist-info/RECORD
