Metadata-Version: 2.1
Name: lazy-alchemy
Version: 1.0.3
Summary: Lazy-Alchemy is a Python package that loads the DB models lazily.
Home-page: https://github.com/satyamsoni2211/lazy_alchemy
Author: Satyam Soni
Author-email: satyamsoni@hotmail.co.uk
License: MIT
Keywords: sqlalchemy,alchemy,mysql,postgres,mssql,sql,sqlite,lazy,performance,orm,mapper,performance,database,lazy,relational,classes,oops,metaclass
Platform: any
Classifier: Development Status :: 5 - Production/Stable
Classifier: Environment :: Console
Classifier: Intended Audience :: Developers
Classifier: Programming Language :: Python
Classifier: Programming Language :: Python :: 3
Classifier: Programming Language :: Python :: 3 :: Only
Classifier: Programming Language :: Python :: 3.6
Classifier: Programming Language :: Python :: 3.7
Classifier: Programming Language :: Python :: 3.8
Classifier: Programming Language :: Python :: 3.9
Classifier: Programming Language :: Python :: Implementation :: CPython
Classifier: Programming Language :: Python :: Implementation :: PyPy
Classifier: Topic :: Software Development :: Libraries :: Python Modules
Classifier: Topic :: Utilities
Classifier: License :: OSI Approved :: MIT License
Requires-Python: >=3.6
License-File: LICENSE
Requires-Dist: sqlalchemy (<2.0)
Provides-Extra: dev
Requires-Dist: pytest ; extra == 'dev'
Requires-Dist: codecoverage ; extra == 'dev'
